dprojectstools/__init__.py
dprojectstools/backups/__init__.py
dprojectstools/backups/restic.py
dprojectstools/commands/__init__.py
dprojectstools/commands/commands.py
dprojectstools/config/__init__.py
dprojectstools/config/config.py
dprojectstools/crypto/__init__.py
dprojectstools/crypto/aes.py
dprojectstools/git/__init__.py
dprojectstools/git/git.py
dprojectstools/secrets/__init__.py
dprojectstools/secrets/secrets.py
dprojectstools-0.0.15.dist-info/LICENSE
dprojectstools-0.0.15.dist-info/METADATA
dprojectstools-0.0.15.dist-info/WHEEL
dprojectstools-0.0.15.dist-info/top_level.txt
dprojectstools-0.0.15.dist-info/RECORD
