Metadata-Version: 2.2
Name: dprojectstools
Version: 0.0.15
Summary: A set of development tools
Author-email: Marc Delos <marcdp@dprojects.com>
Project-URL: Homepage, https://github.com/marcdp/dprojectstools
Project-URL: Issues, https://github.com/marcdp/dprojectstools/issues
Classifier: Programming Language :: Python :: 3
Classifier: License :: OSI Approved :: MIT License
Classifier: Operating System :: OS Independent
Requires-Python: >=3.8
License-File: LICENSE
Requires-Dist: keyring>=25.6.0
Requires-Dist: cryptography>=44.0.0
